src/CICDManagerAPIClient/apli_client.py
src/CICDManagerAPIClient/test_classes.py
src/DescriptorParser/parser.py
src/TestingDescriptorGenerator/descriptor_generator.py
src/__init__.py
src/helpers/base_testing_descriptor.py
src/helpers/beatiful_prints.py
src/helpers/connection_point_tags.py
src/helpers/constants.py
src/helpers/prompts.py
src/main.py
src/tests/__init__.py
src/tests/resources/hackfest_multivdu_nsd.yaml
src/tests/test_cli.py
src/tests/test_output.yaml
5gasp_cli-0.4.0.dist-info/LICENSE
5gasp_cli-0.4.0.dist-info/METADATA
5gasp_cli-0.4.0.dist-info/WHEEL
5gasp_cli-0.4.0.dist-info/entry_points.txt
5gasp_cli-0.4.0.dist-info/RECORD
