Metadata-Version: 2.1
Name: 5gasp-cli
Version: 0.4.0
Summary: 5GASP CLI to create testing descriptors.
Home-page: https://github.com/5gasp/5gasp-cli
Keywords: 5gasp,5g,network apps
Author: Eduardo Santos
Author-email: eduardosantoshf@av.it.pt
Requires-Python: >=3.8,<4.0
Classifier: Programming Language :: Python :: 3
Classifier: Programming Language :: Python :: 3.8
Classifier: Programming Language :: Python :: 3.9
Classifier: Programming Language :: Python :: 3.10
Classifier: Programming Language :: Python :: 3.11
Requires-Dist: PyYAML (==6.0)
Requires-Dist: poetry (==1.4.2)
Requires-Dist: pytest (==7.2.1)
Requires-Dist: requests (==2.30.0)
Requires-Dist: typer[all] (>=0.7.0,<0.8.0)
Project-URL: Repository, https://github.com/5gasp/5gasp-cli
